MANIFEST.in
README.rst
setup.py
aliyun_python_sdk_industry_brain.egg-info/PKG-INFO
aliyun_python_sdk_industry_brain.egg-info/SOURCES.txt
aliyun_python_sdk_industry_brain.egg-info/dependency_links.txt
aliyun_python_sdk_industry_brain.egg-info/requires.txt
aliyun_python_sdk_industry_brain.egg-info/top_level.txt
aliyunsdkindustry_brain/__init__.py
aliyunsdkindustry_brain/request/__init__.py
aliyunsdkindustry_brain/request/v20190630/AsyncResponsePostRequest.py
aliyunsdkindustry_brain/request/v20190630/GetAlgorithmHistoryResultRequest.py
aliyunsdkindustry_brain/request/v20190630/GetPointReckoningValueRequest.py
aliyunsdkindustry_brain/request/v20190630/GetPointSampleValueRequest.py
aliyunsdkindustry_brain/request/v20190630/GetServiceResultAsyncRequest.py
aliyunsdkindustry_brain/request/v20190630/InvokeServiceAsyncRequest.py
aliyunsdkindustry_brain/request/v20190630/InvokeServiceRequest.py
aliyunsdkindustry_brain/request/v20190630/__init__.py